empytools/__init__.py
empytools/time_freq_data.py
empytools/utils.py
empytools-0.0.3.dist-info/METADATA
empytools-0.0.3.dist-info/WHEEL
empytools-0.0.3.dist-info/licenses/LICENSE
empytools-0.0.3.dist-info/RECORD
