Metadata-Version: 2.4
Name: empytools
Version: 0.0.3
Author-email: Mark Pude <markpude@gmail.com>
License: MIT
License-File: LICENSE
Requires-Python: >=3.11
Requires-Dist: matplotlib<4.0.0,>=3.10.1
Requires-Dist: numpy<3.0.0,>=2.2.4
